pymemcache/__init__.py
pymemcache/exceptions.py
pymemcache/fallback.py
pymemcache/pool.py
pymemcache/serde.py
pymemcache/client/__init__.py
pymemcache/client/base.py
pymemcache/client/hash.py
pymemcache/client/murmur3.py
pymemcache/client/rendezvous.py
pymemcache/client/retrying.py
pymemcache/test/__init__.py
pymemcache/test/conftest.py
pymemcache/test/test_benchmark.py
pymemcache/test/test_client.py
pymemcache/test/test_client_hash.py
pymemcache/test/test_client_retry.py
pymemcache/test/test_integration.py
pymemcache/test/test_rendezvous.py
pymemcache/test/test_serde.py
pymemcache/test/test_utils.py
pymemcache/test/utils.py
pymemcache-3.5.2.dist-info/LICENSE.txt
pymemcache-3.5.2.dist-info/METADATA
pymemcache-3.5.2.dist-info/WHEEL
pymemcache-3.5.2.dist-info/top_level.txt
pymemcache-3.5.2.dist-info/RECORD
