Metadata-Version: 2.1
Name: pymemcache
Version: 3.5.2
Summary: A comprehensive, fast, pure Python memcached client
Home-page: https://github.com/pinterest/pymemcache
Author: Jon Parise
Author-email: jon@pinterest.com
License: Apache License 2.0
Keywords: memcache,client,database
Platform: UNKNOWN
Classifier: Programming Language :: Python
Classifier: Programming Language :: Python :: 2.7
Classifier: Programming Language :: Python :: 3.6
Classifier: Programming Language :: Python :: 3.7
Classifier: Programming Language :: Python :: 3.8
Classifier: Programming Language :: Python :: 3.9
Classifier: Programming Language :: Python :: Implementation :: PyPy
Classifier: License :: OSI Approved :: Apache Software License
Classifier: Topic :: Database
License-File: LICENSE.txt
